setup.py
src/teqoa-water-use-equations/water-use-equations.py
teqoa_water_use_equations_teqoa-0.0.1.dist-info/METADATA
teqoa_water_use_equations_teqoa-0.0.1.dist-info/WHEEL
teqoa_water_use_equations_teqoa-0.0.1.dist-info/licenses/LICENCE
teqoa_water_use_equations_teqoa-0.0.1.dist-info/RECORD
